iyzipay/__init__.py
iyzipay/iyzipay_resource.py
iyzipay/pki_builder.py
iyzipay_fork-1.0.38.dist-info/LICENSE
iyzipay_fork-1.0.38.dist-info/METADATA
iyzipay_fork-1.0.38.dist-info/WHEEL
iyzipay_fork-1.0.38.dist-info/top_level.txt
iyzipay_fork-1.0.38.dist-info/RECORD
