Metadata-Version: 2.1
Name: iyzipay-fork
Version: 1.0.38
Summary: iyzipay api python client
Home-page: https://github.com/iyzico/iyzipay-python
Author: iyzico
Author-email: Iyzico <iyzico-ci@iyzico.com>
License: The MIT License (MIT)
Classifier: Intended Audience :: Developers
Classifier: License :: OSI Approved :: MIT License
Classifier: Operating System :: OS Independent
Classifier: Programming Language :: Python
Classifier: Programming Language :: Python :: 3
Classifier: Programming Language :: Python :: 3.6
Classifier: Programming Language :: Python :: 3.7
Classifier: Programming Language :: Python :: 3.8
Classifier: Programming Language :: Python :: Implementation :: PyPy
Classifier: Topic :: Software Development :: Libraries :: Python Modules
Requires-Python: >=3.6
License-File: LICENSE
